{
    "ch01": 614,
    "ch02": 209,
    "ch03": 536,
    "ch04": 603,
    "ch05": 487,
    "ch06": 504,
    "ch07": 463,
    "ch08": 636,
    "ch09": 184,
    "ch10": 576,
    "ch11": 544,
    "ch12": 657,
    "ch13": 513,
    "ch14": 620,
    "ch15": 667,
    "ch16": 208,
    "ch17": 430,
    "ch18": 399,
    "ch19": 723,
    "ch20": 728,
    "ch21": 306,
    "ch22": 489,
    "ch23": 627,
    "ch24": 152,
    "ch25": 728,
    "ch26": 769,
    "ch27": 213,
    "ch28": 140,
    "ch29": 152,
    "ch30": 513,
    "ch31": 582,
    "ch32": 745,
    "ch33": 274,
    "ch34": 446
}