{
    "ch01": 114,
    "ch02": 329,
    "ch03": 486,
    "ch04": 784,
    "ch05": 226,
    "ch06": 585,
    "ch07": 736,
    "ch08": 506,
    "ch09": 319,
    "ch10": 236,
    "ch11": 311,
    "ch12": 149,
    "ch13": 788,
    "ch14": 788,
    "ch15": 457,
    "ch16": 211,
    "ch17": 791,
    "ch18": 268,
    "ch19": 224,
    "ch20": 437,
    "ch21": 320,
    "ch22": 181,
    "ch23": 471,
    "ch24": 424,
    "ch25": 145,
    "ch26": 262,
    "ch27": 526,
    "ch28": 150,
    "ch29": 145,
    "ch30": 303,
    "ch31": 160,
    "ch32": 580,
    "ch33": 166,
    "ch34": 645,
    "ch35": 694
}